<?xml version="1.0" encoding="utf-8" ?>
<dwsync>
<file name="2sara1.jpg" server="ftp.erieit.edu//html/" local="130011094722190215" remote="130010986800000000" Dst="-1" />
<file name="2sara2.jpg" server="ftp.erieit.edu//html/" local="130011094761594155" remote="130010986800000000" Dst="-1" />
<file name="2sara3.jpg" server="ftp.erieit.edu//html/" local="130011094802748270" remote="130010986800000000" Dst="-1" />
<file name="Zuck, Sara.JPG" server="ftp.erieit.edu//html/" local="130005823652841934" remote="130010986800000000" Dst="-1" />
<file name="sara_zuck.jpg" server="ftp.erieit.edu//html/" local="130011095496027591" remote="130010988000000000" Dst="-1" />
<file name="2sara1.jpg" server="ftp.toniguy-erie.org/domains/erieit.edu/html/newsite/CI_eit_website/" local="130011094722190215" remote="130355761200000000" Dst="1" />
<file name="2sara2.jpg" server="ftp.toniguy-erie.org/domains/erieit.edu/html/newsite/CI_eit_website/" local="130011094761594155" remote="130355761200000000" Dst="1" />
<file name="2sara3.jpg" server="ftp.toniguy-erie.org/domains/erieit.edu/html/newsite/CI_eit_website/" local="130011094802748270" remote="130355761200000000" Dst="1" />
<file name="sara_zuck.jpg" server="ftp.toniguy-erie.org/domains/erieit.edu/html/newsite/CI_eit_website/" local="130011095496027591" remote="130355761200000000" Dst="1" />
<file name="Zuck, Sara.JPG" server="ftp.toniguy-erie.org/domains/erieit.edu/html/newsite/CI_eit_website/" local="130005823652841934" remote="130355761200000000" Dst="1" />
<file name="2sara1.jpg" server="ftp.toniguy-erie.org/domains/erieit.edu/html/" local="130011094722190215" remote="130439383200000000" Dst="2" />
<file name="2sara2.jpg" server="ftp.toniguy-erie.org/domains/erieit.edu/html/" local="130011094761594155" remote="130439383200000000" Dst="2" />
<file name="2sara3.jpg" server="ftp.toniguy-erie.org/domains/erieit.edu/html/" local="130011094802748270" remote="130439383200000000" Dst="2" />
<file name="sara_zuck.jpg" server="ftp.toniguy-erie.org/domains/erieit.edu/html/" local="130011095496027591" remote="130439383200000000" Dst="2" />
<file name="Zuck, Sara.JPG" server="ftp.toniguy-erie.org/domains/erieit.edu/html/" local="130005823652841934" remote="130439383200000000" Dst="2" />
</dwsync>