<?xml version="1.0" encoding="utf-8" ?>
<dwsync>
<file name="downloads.html" server="ftp.toniguy-erie.org/domains/erieit.edu/html/" local="130338594058431861" remote="130337955600000000" Dst="1" />
<file name="index.html" server="ftp.toniguy-erie.org/domains/erieit.edu/html/" local="130338594067802798" remote="130337955600000000" Dst="1" />
<file name="troubleshooting.html" server="ftp.toniguy-erie.org/domains/erieit.edu/html/" local="130338594067862804" remote="130337955600000000" Dst="1" />
<file name="upgrade_120.html" server="ftp.toniguy-erie.org/domains/erieit.edu/html/" local="130338594068172835" remote="130337955600000000" Dst="1" />
<file name="upgrade_130.html" server="ftp.toniguy-erie.org/domains/erieit.edu/html/" local="130338594076623680" remote="130337955600000000" Dst="1" />
<file name="upgrade_131.html" server="ftp.toniguy-erie.org/domains/erieit.edu/html/" local="130338594076653683" remote="130337955600000000" Dst="1" />
<file name="upgrade_132.html" server="ftp.toniguy-erie.org/domains/erieit.edu/html/" local="130338594076963714" remote="130337955600000000" Dst="1" />
<file name="upgrade_133.html" server="ftp.toniguy-erie.org/domains/erieit.edu/html/" local="130338594088174835" remote="130337955600000000" Dst="1" />
<file name="upgrade_140.html" server="ftp.toniguy-erie.org/domains/erieit.edu/html/" local="130338594088204838" remote="130337955600000000" Dst="1" />
<file name="upgrade_141.html" server="ftp.toniguy-erie.org/domains/erieit.edu/html/" local="130338594088354853" remote="130337955600000000" Dst="1" />
<file name="upgrade_150.html" server="ftp.toniguy-erie.org/domains/erieit.edu/html/" local="130338594096785696" remote="130337955600000000" Dst="1" />
<file name="upgrade_152.html" server="ftp.toniguy-erie.org/domains/erieit.edu/html/" local="130338594096825700" remote="130337955600000000" Dst="1" />
<file name="upgrade_153.html" server="ftp.toniguy-erie.org/domains/erieit.edu/html/" local="130338594097155733" remote="130337955600000000" Dst="1" />
<file name="upgrade_154.html" server="ftp.toniguy-erie.org/domains/erieit.edu/html/" local="130338594105616579" remote="130337955600000000" Dst="1" />
<file name="upgrade_160.html" server="ftp.toniguy-erie.org/domains/erieit.edu/html/" local="130338594105656583" remote="130337955600000000" Dst="1" />
<file name="upgrade_161.html" server="ftp.toniguy-erie.org/domains/erieit.edu/html/" local="130338594106196637" remote="130337955600000000" Dst="1" />
<file name="upgrade_162.html" server="ftp.toniguy-erie.org/domains/erieit.edu/html/" local="130338594114157433" remote="130337955600000000" Dst="1" />
<file name="upgrade_163.html" server="ftp.toniguy-erie.org/domains/erieit.edu/html/" local="130338594114197437" remote="130337955600000000" Dst="1" />
<file name="upgrade_170.html" server="ftp.toniguy-erie.org/domains/erieit.edu/html/" local="130338594114537471" remote="130337955600000000" Dst="1" />
<file name="upgrade_171.html" server="ftp.toniguy-erie.org/domains/erieit.edu/html/" local="130338594122818299" remote="130337955600000000" Dst="1" />
<file name="upgrade_172.html" server="ftp.toniguy-erie.org/domains/erieit.edu/html/" local="130338594122848302" remote="130337955600000000" Dst="1" />
<file name="upgrade_200.html" server="ftp.toniguy-erie.org/domains/erieit.edu/html/" local="130338594123158333" remote="130337955600000000" Dst="1" />
<file name="upgrade_202.html" server="ftp.toniguy-erie.org/domains/erieit.edu/html/" local="130338594131509168" remote="130337955600000000" Dst="1" />
<file name="upgrade_201.html" server="ftp.toniguy-erie.org/domains/erieit.edu/html/" local="130338594131669184" remote="130337955600000000" Dst="1" />
<file name="upgrade_203.html" server="ftp.toniguy-erie.org/domains/erieit.edu/html/" local="130338594131879205" remote="130337955600000000" Dst="1" />
<file name="upgrade_210.html" server="ftp.toniguy-erie.org/domains/erieit.edu/html/" local="130338594145000517" remote="130337955600000000" Dst="1" />
<file name="upgrade_211.html" server="ftp.toniguy-erie.org/domains/erieit.edu/html/" local="130338594145020519" remote="130337955600000000" Dst="1" />
<file name="upgrade_212.html" server="ftp.toniguy-erie.org/domains/erieit.edu/html/" local="130338594145060523" remote="130337955600000000" Dst="1" />
<file name="upgrade_214.html" server="ftp.toniguy-erie.org/domains/erieit.edu/html/" local="130338594153691386" remote="130337955600000000" Dst="1" />
<file name="upgrade_213.html" server="ftp.toniguy-erie.org/domains/erieit.edu/html/" local="130338594153851402" remote="130337955600000000" Dst="1" />
<file name="upgrade_b11.html" server="ftp.toniguy-erie.org/domains/erieit.edu/html/" local="130338594154121429" remote="130337955600000000" Dst="1" />
<file name="upgrading.html" server="ftp.toniguy-erie.org/domains/erieit.edu/html/" local="130338594162602277" remote="130337955600000000" Dst="1" />
</dwsync>